{
    "offices": [
        {
            "phone": "+7 (812) 209-19-68",
            "address": "посёлок Белоостров, Новое шоссе, 53",
            "scale": 14,
            "coord": "",
            "gmap": "1l2m0hH8qr-P77x0JZ9aowXtxrkhyM3k&ehbc=2E312F",
            "ymap": "3A7b00acaaa393f3fedf5bbe6c1c03627f62116b2766eaa0c7de3a843beca9c0a5"
        }
    ],
    "toponim": {
        "base": {
            "standart": "Белоостров",
            "abr": "Белоостров",
            "full": "Белоостров и Ленинградская область",
            "abr_full": "Белоостров и ЛО"
        },
        "where": {
            "standart": "в Белоострове",
            "abr": "в Белоострове",
            "full": "в Белоострове и Ленинградской области",
            "abr_full": "в Белоострове и ЛО"
        },
        "on": {
            "standart": "по Белоострову",
            "abr": "по Белоострову",
            "full": "по Белоострову и Ленинградской области",
            "abr_full": "по Белоострову и ЛО"
        },
        "what": {
            "standart": "Белоострова",
            "abr": "Белоострова",
            "full": "Белоострова и Ленинградской области",
            "abr_full": "Белоострова и ЛО"
        },
        "oblast": {
            "standart": "Ленинградская область",
            "abr": "ЛО",
            "any": "Ленинградской области",
            "anyabr": "ЛО"
        }
    },
    "oblast": {
        "standart": null,
        "abr": "ЛО",
        "any": "Ленинградской области",
        "anyabr": "ЛО"
    },
    "subdomain_key": "beloostrov"
}